tiktoken_cli/__init__.py
tiktoken_cli-1.0.0.dist-info/METADATA
tiktoken_cli-1.0.0.dist-info/WHEEL
tiktoken_cli-1.0.0.dist-info/entry_points.txt
tiktoken_cli-1.0.0.dist-info/licenses/LICENSE
tiktoken_cli-1.0.0.dist-info/RECORD
