Metadata-Version: 2.1
Name: tiktoken-cli
Version: 1.0.0
Summary: Simple wrapper around tiktoken to use it in your favorite language.
Project-URL: Source, https://github.com/jplumail/tiktoken-cli
Author-email: jplumail <jeanplumail76@gmail.com>
License-Expression: MIT
License-File: LICENSE
Requires-Python: >=3.7
Requires-Dist: click
Requires-Dist: tiktoken
